Lab5/part 2_3/cont_8bit_adder.v
`timescale 1ns/1ps
module cont_8bit_adder(sum,cout,a,b,cin);
    input [7:0] a,b;
    input cin;
    output [7:0] sum;
    output cout;

    assign {cout,sum} = a+b+cin;
endmodule

Lab5/part 2_3/testbench_cont_8bit_adder.v
`timescale 1ns/1ps

module testbench_cont_8bit_adder;

reg [7:0] a, b;
reg cin;
wire [7:0] sum;
wire cout;

cont_8bit_adder DUT(sum,cout,a,b,cin);


initial begin
    $dumpfile("cont_8bit_adder.vcd");
    $dumpvars;
end

initial
begin
    a=8'b11111111;
    b=8'b11111111;
    cin = 1'b0;
end

always #1
begin
    if(($stime%256)==1)
        a=a+8'b00000001;

    b=b+8'b00000001;
    $monitor("%4dns monitor: a=%d b=%d cin=%d sum=%d cout=%d",$stime, a, b, cin, sum, cout);
end

initial #65537 $finish;

endmodule

Lab5/part 2_3/cont_8bit_adder.vcd
$date
	Sun Apr 15 22:01:09 2018
$end
$version
	Icarus Verilog
$end
$timescale
	1ps
$end
$scope module testbench_cont_8bit_adder $end
$var wire 8 ! sum [7:0] $end
$var wire 1 " cout $end
$var reg 8 # a [7:0] $end
$var reg 8 $ b [7:0] $end
$var reg 1 % cin $end
$scope module DUT $end
$var wire 8 & a [7:0] $end
$var wire 8 ' b [7:0] $end
$var wire 1 % cin $end
$var wire 8 ( sum [7:0] $end
$var wire 1 " cout $end
$upscope $end
$upscope $end
$enddefinitions $end
#0
$dumpvars
b11111110 (
b11111111 '
b11111111 &
0%
b11111111 $
b11111111 #
1"
b11111110 !
$end
#1000
b0 !
b0 (
0"
b0 $
b0 '
b0 #
b0 &
#2000
b1 !
b1 (
b1 $
b1 '
#3000
b10 !
b10 (
b10 $
b10 '
#4000
b11 !
b11 (
b11 $
b11 '
#5000
b100 !
b100 (
b100 $
b100 '
#6000
b101 !
b101 (
b101 $
b101 '
#7000
b110 !
b110 (
b110 $
b110 '
#8000
b111 !
b111 (
b111 $
b111 '
#9000
b1000 !
b1000 (
b1000 $
b1000 '
#10000
b1001 !
b1001 (
b1001 $
b1001 '
#11000
b1010 !
b1010 (
b1010 $
b1010 '
#12000
b1011 !
b1011 (
b1011 $
b1011 '
#13000
b1100 !
b1100 (
b1100 $
b1100 '
#14000
b1101 !
b1101 (
b1101 $
b1101 '
#15000
b1110 !
b1110 (
b1110 $
b1110 '
#16000
b1111 !
b1111 (
b1111 $
b1111 '
#17000
b10000 !
b10000 (
b10000 $
b10000 '
#18000
b10001 !
b10001 (
b10001 $
b10001 '
#19000
b10010 !
b10010 (
b10010 $
b10010 '
#20000
b10011 !
b10011 (
b10011 $
b10011 '
#21000
b10100 !
b10100 (
b10100 $
b10100 '
#22000
b10101 !
b10101 (
b10101 $
b10101 '
#23000
b10110 !
b10110 (
b10110 $
b10110 '
#24000
b10111 !
b10111 (
b10111 $
b10111 '
#25000
b11000 !
b11000 (
b11000 $
b11000 '
#26000
b11001 !
b11001 (
b11001 $
b11001 '
#27000
b11010 !
b11010 (
b11010 $
b11010 '
#28000
b11011 !
b11011 (
b11011 $
b11011 '
#29000
b11100 !
b11100 (
b11100 $
b11100 '
#30000
b11101 !
b11101 (
b11101 $
b11101 '
#31000
b11110 !
b11110 (
b11110 $
b11110 '
#32000
b11111 !
b11111 (
b11111 $
b11111 '
#33000
b100000 !
b100000 (
b100000 $
b100000 '
#34000
b100001 !
b100001 (
b100001 $
b100001 '
#35000
b100010 !
b100010 (
b100010 $
b100010 '
#36000
b100011 !
b100011 (
b100011 $
b100011 '
#37000
b100100 !
b100100 (
b100100 $
b100100 '
#38000
b100101 !
b100101 (
b100101 $
b100101 '
#39000
b100110 !
b100110 (
b100110 $
b100110 '
#40000
b100111 !
b100111 (
b100111 $
b100111 '
#41000
b101000 !
b101000 (
b101000 $
b101000 '
#42000
b101001 !
b101001 (
b101001 $
b101001 '
#43000
b101010 !
b101010 (
b101010 $
b101010 '
#44000
b101011 !
b101011 (
b101011 $
b101011 '
#45000
b101100 !
b101100 (
b101100 $
b101100 '
#46000
b101101 !
b101101 (
b101101 $
b101101 '
#47000
b101110 !
b101110 (
b101110 $
b101110 '
#48000
b101111 !
b101111 (
b101111 $
b101111 '
#49000
b110000 !
b110000 (
b110000 $
b110000 '
#50000
b110001 !
b110001 (
b110001 $
b110001 '
#51000
b110010 !
b110010 (
b110010 $
b110010 '
#52000
b110011 !
b110011 (
b110011 $
b110011 '
#53000
b110100 !
b110100 (
b110100 $
b110100 '
#54000
b110101 !
b110101 (
b110101 $
b110101 '
#55000
b110110 !
b110110 (
b110110 $
b110110 '
#56000
b110111 !
b110111 (
b110111 $
b110111 '
#57000
b111000 !
b111000 (
b111000 $
b111000 '
#58000
b111001 !
b111001 (
b111001 $
b111001 '
#59000
b111010 !
b111010 (
b111010 $
b111010 '
#60000
b111011 !
b111011 (
b111011 $
b111011 '
#61000
b111100 !
b111100 (
b111100 $
b111100 '
#62000
b111101 !
b111101 (
b111101 $
b111101 '
#63000
b111110 !
b111110 (
b111110 $
b111110 '
#64000
b111111 !
b111111 (
b111111 $
b111111 '
#65000
b1000000 !
b1000000 (
b1000000 $
b1000000 '
#66000
b1000001 !
b1000001 (
b1000001 $
b1000001 '
#67000
b1000010 !
b1000010 (
b1000010 $
b1000010 '
#68000
b1000011 !
b1000011 (
b1000011 $
b1000011 '
#69000
b1000100 !
b1000100 (
b1000100 $
b1000100 '
#70000
b1000101 !
b1000101 (
b1000101 $
b1000101 '
#71000
b1000110 !
b1000110 (
b1000110 $
b1000110 '
#72000
b1000111 !
b1000111 (
b1000111 $
b1000111 '
#73000
b1001000 !
b1001000 (
b1001000 $
b1001000 '
#74000
b1001001 !
b1001001 (
b1001001 $
b1001001 '
#75000
b1001010 !
b1001010 (
b1001010 $
b1001010 '
#76000
b1001011 !
b1001011 (
b1001011 $
b1001011 '
#77000
b1001100 !
b1001100 (
b1001100 $
b1001100 '
#78000
b1001101 !
b1001101 (
b1001101 $
b1001101 '
#79000
b1001110 !
b1001110 (
b1001110 $
b1001110 '
#80000
b1001111 !
b1001111 (
b1001111 $
b1001111 '
#81000
b1010000 !
b1010000 (
b1010000 $
b1010000 '
#82000
b1010001 !
b1010001 (
b1010001 $
b1010001 '
#83000
b1010010 !
b1010010 (
b1010010 $
b1010010 '
#84000
b1010011 !
b1010011 (
b1010011 $
b1010011 '
#85000
b1010100 !
b1010100 (
b1010100 $
b1010100 '
#86000
b1010101 !
b1010101 (
b1010101 $
b1010101 '
#87000
b1010110 !
b1010110 (
b1010110 $
b1010110 '
#88000
b1010111 !
b1010111 (
b1010111 $
b1010111 '
#89000
b1011000 !
b1011000 (
b1011000 $
b1011000 '
#90000
b1011001 !
b1011001 (
b1011001 $
b1011001 '
#91000
b1011010 !
b1011010 (
b1011010 $
b1011010 '
#92000
b1011011 !
b1011011 (
b1011011 $
b1011011 '
#93000
b1011100 !
b1011100 (
b1011100 $
b1011100 '
#94000
b1011101 !
b1011101 (
b1011101 $
b1011101 '
#95000
b1011110 !
b1011110 (
b1011110 $
b1011110 '
#96000
b1011111 !
b1011111 (
b1011111 $
b1011111 '
#97000
b1100000 !
b1100000 (
b1100000 $
b1100000 '
#98000
b1100001 !
b1100001 (
b1100001 $
b1100001 '
#99000
b1100010 !
b1100010 (
b1100010 $
b1100010 '
#100000
b1100011 !
b1100011 (
b1100011 $
b1100011 '
#101000
b1100100 !
b1100100 (
b1100100 $
b1100100 '
#102000
b1100101 !
b1100101 (
b1100101 $
b1100101 '
#103000
b1100110 !
b1100110 (
b1100110 $
b1100110 '
#104000
b1100111 !
b1100111 (
b1100111 $
b1100111 '
#105000
b1101000 !
b1101000 (
b1101000 $
b1101000 '
#106000
b1101001 !
b1101001 (
b1101001 $
b1101001 '
#107000
b1101010 !
b1101010 (
b1101010 $
b1101010 '
#108000
b1101011 !
b1101011 (
b1101011 $
b1101011 '
#109000
b1101100 !
b1101100 (
b1101100 $
b1101100 '
#110000
b1101101 !
b1101101 (
b1101101 $
b1101101 '
#111000
b1101110 !
b1101110 (
b1101110 $
b1101110 '
#112000
b1101111 !
b1101111 (
b1101111 $
b1101111 '
#113000
b1110000 !
b1110000 (
b1110000 $
b1110000 '
#114000
b1110001 !
b1110001 (
b1110001 $
b1110001 '
#115000
b1110010 !
b1110010 (
b1110010 $
b1110010 '
#116000
b1110011 !
b1110011 (
b1110011 $
b1110011 '
#117000
b1110100 !
b1110100 (
b1110100 $
b1110100 '
#118000
b1110101 !
b1110101 (
b1110101 $
b1110101 '
#119000
b1110110 !
b1110110 (
b1110110 $
b1110110 '
#120000
b1110111 !
b1110111 (
b1110111 $
b1110111 '
#121000
b1111000 !
b1111000 (
b1111000 $
b1111000 '
#122000
b1111001 !
b1111001 (
b1111001 $
b1111001 '
#123000
b1111010 !
b1111010 (
b1111010 $
b1111010 '
#124000
b1111011 !
b1111011 (
b1111011 $
b1111011 '
#125000
b1111100 !
b1111100 (
b1111100 $
b1111100 '
#126000
b1111101 !
b1111101 (
b1111101 $
b1111101 '
#127000
b1111110 !
b1111110 (
b1111110 $
b1111110 '
#128000
b1111111 !
b1111111 (
b1111111 $
b1111111 '
#129000
b10000000 !
b10000000 (
b10000000 $
b10000000 '
#130000
b10000001 !
b10000001 (
b10000001 $
b10000001 '
#131000
b10000010 !
b10000010 (
b10000010 $
b10000010 '
#132000
b10000011 !
b10000011 (
b10000011 $
b10000011 '
#133000
b10000100 !
b10000100 (
b10000100 $
b10000100 '
#134000
b10000101 !
b10000101 (
b10000101 $
b10000101 '
#135000
b10000110 !
b10000110 (
b10000110 $
b10000110 '
#136000
b10000111 !
b10000111 (
b10000111 $
b10000111 '
#137000
b10001000 !
b10001000 (
b10001000 $
b10001000 '
#138000
b10001001 !
b10001001 (
b10001001 $
b10001001 '
#139000
b10001010 !
b10001010 (
b10001010 $
b10001010 '
#140000
b10001011 !
b10001011 (
b10001011 $
b10001011 '
#141000
b10001100 !
b10001100 (
b10001100 $
b10001100 '
#142000
b10001101 !
b10001101 (
b10001101 $
b10001101 '
#143000
b10001110 !
b10001110 (
b10001110 $
b10001110 '
#144000
b10001111 !
b10001111 (
b10001111 $
b10001111 '
#145000
b10010000 !
b10010000 (
b10010000 $
b10010000 '
#146000
b10010001 !
b10010001 (
b10010001 $
b10010001 '
#147000
b10010010 !
b10010010 (
b10010010 $
b10010010 '
#148000
b10010011 !
b10010011 (
b10010011 $
b10010011 '
#149000
b10010100 !
b10010100 (
b10010100 $
b10010100 '
#150000
b10010101 !
b10010101 (
b10010101 $
b10010101 '
#151000
b10010110 !
b10010110 (
b10010110 $
b10010110 '
#152000
b10010111 !
b10010111 (
b10010111 $
b10010111 '
#153000
b10011000 !
b10011000 (
b10011000 $
b10011000 '
#154000
b10011001 !
b10011001 (
b10011001 $
b10011001 '
#155000
b10011010 !
b10011010 (
b10011010 $
b10011010 '
#156000
b10011011 !
b10011011 (
b10011011 $
b10011011 '
#157000
b10011100 !
b10011100 (
b10011100 $
b10011100 '
#158000
b10011101 !
b10011101 (
b10011101 $
b10011101 '
#159000
b10011110 !
b10011110 (
b10011110 $
b10011110 '
#160000
b10011111 !
b10011111 (
b10011111 $
b10011111 '
#161000
b10100000 !
b10100000 (
b10100000 $
b10100000 '
#162000
b10100001 !
b10100001 (
b10100001 $
b10100001 '
#163000
b10100010 !
b10100010 (
b10100010 $
b10100010 '
#164000
b10100011 !
b10100011 (
b10100011 $
b10100011 '
#165000
b10100100 !
b10100100 (
b10100100 $
b10100100 '
#166000
b10100101 !
b10100101 (
b10100101 $
b10100101 '
#167000
b10100110 !
b10100110 (
b10100110 $
b10100110 '
#168000
b10100111 !
b10100111 (
b10100111 $
b10100111 '
#169000
b10101000 !
b10101000 (
b10101000 $
b10101000 '
#170000
b10101001 !
b10101001 (
b10101001 $
b10101001 '
#171000
b10101010 !
b10101010 (
b10101010 $
b10101010 '
#172000
b10101011 !
b10101011 (
b10101011 $
b10101011 '
#173000
b10101100 !
b10101100 (
b10101100 $
b10101100 '
#174000
b10101101 !
b10101101 (
b10101101 $
b10101101 '
#175000
b10101110 !
b10101110 (
b10101110 $
b10101110 '
#176000
b10101111 !
b10101111 (
b10101111 $
b10101111 '
#177000
b10110000 !
b10110000 (
b10110000 $
b10110000 '
#178000
b10110001 !
b10110001 (
b10110001 $
b10110001 '
#179000
b10110010 !
b10110010 (
b10110010 $
b10110010 '
#180000
b10110011 !
b10110011 (
b10110011 $
b10110011 '
#181000
b10110100 !
b10110100 (
b10110100 $
b10110100 '
#182000
b10110101 !
b10110101 (
b10110101 $
b10110101 '
#183000
b10110110 !
b10110110 (
b10110110 $
b10110110 '
#184000
b10110111 !
b10110111 (
b10110111 $
b10110111 '
#185000
b10111000 !
b10111000 (
b10111000 $
b10111000 '
#186000
b10111001 !
b10111001 (
b10111001 $
b10111001 '
#187000
b10111010 !
b10111010 (
b10111010 $
b10111010 '
#188000
b10111011 !
b10111011 (
b10111011 $
b10111011 '
#189000
b10111100 !
b10111100 (
b10111100 $
b10111100 '
#190000
b10111101 !
b10111101 (
b10111101 $
b10111101 '
#191000
b10111110 !
b10111110 (
b10111110 $
b10111110 '
#192000
b10111111 !
b10111111 (
b10111111 $
b10111111 '
#193000
b11000000 !
b11000000 (
b11000000 $
b11000000 '
#194000
b11000001 !
b11000001 (
b11000001 $
b11000001 '
#195000
b11000010 !
b11000010 (
b11000010 $
b11000010 '
#196000
b11000011 !
b11000011 (
b11000011 $
b11000011 '
#197000
b11000100 !
b11000100 (
b11000100 $
b11000100 '
#198000
b11000101 !
b11000101 (
b11000101 $
b11000101 '
#199000
b11000110 !
b11000110 (
b11000110 $
b11000110 '
#200000
b11000111 !
b11000111 (
b11000111 $
b11000111 '
#201000
b11001000 !
b11001000 (
b11001000 $
b11001000 '
#202000
b11001001 !
b11001001 (
b11001001 $
b11001001 '
#203000
b11001010 !
b11001010 (
b11001010 $
b11001010 '
#204000
b11001011 !
b11001011 (
b11001011 $
b11001011 '
#205000
b11001100 !
b11001100 (
b11001100 $
b11001100 '
#206000
b11001101 !
b11001101 (
b11001101 $
b11001101 '
#207000
b11001110 !
b11001110 (
b11001110 $
b11001110 '
#208000
b11001111 !
b11001111 (
b11001111 $
b11001111 '
#209000
b11010000 !
b11010000 (
b11010000 $
b11010000 '
#210000
b11010001 !
b11010001 (
b11010001 $
b11010001 '
#211000
b11010010 !
b11010010 (
b11010010 $
b11010010 '
#212000
b11010011 !
b11010011 (
b11010011 $
b11010011 '
#213000
b11010100 !
b11010100 (
b11010100 $
b11010100 '
#214000
b11010101 !
b11010101 (
b11010101 $
b11010101 '
#215000
b11010110 !
b11010110 (
b11010110 $
b11010110 '
#216000
b11010111 !
b11010111 (
b11010111 $
b11010111 '
#217000
b11011000 !
b11011000 (
b11011000 $
b11011000 '
#218000
b11011001 !
b11011001 (
b11011001 $
b11011001 '
#219000
b11011010 !
b11011010 (
b11011010 $
b11011010 '
#220000
b11011011 !
b11011011 (
b11011011 $
b11011011 '
#221000
b11011100 !
b11011100 (
b11011100 $
b11011100 '
#222000
b11011101 !
b11011101 (
b11011101 $
b11011101 '
#223000
b11011110 !
b11011110 (
b11011110 $
b11011110 '
#224000
b11011111 !
b11011111 (
b11011111 $
b11011111 '
#225000
b11100000 !
b11100000 (
b11100000 $
b11100000 '
#226000
b11100001 !
b11100001 (
b11100001 $
b11100001 '
#227000
b11100010 !
b11100010 (
b11100010 $
b11100010 '
#228000
b11100011 !
b11100011 (
b11100011 $
b11100011 '
#229000
b11100100 !
b11100100 (
b11100100 $
b11100100 '
#230000
b11100101 !
b11100101 (
b11100101 $
b11100101 '
#231000
b11100110 !
b11100110 (
b11100110 $
b11100110 '
#232000
b11100111 !
b11100111 (
b11100111 $
b11100111 '
#233000
b11101000 !
b11101000 (
b11101000 $
b11101000 '
#234000
b11101001 !
b11101001 (
b11101001 $
b11101001 '
#235000
b11101010 !
b11101010 (
b11101010 $
b11101010 '
#236000
b11101011 !
b11101011 (
b11101011 $
b11101011 '
#237000
b11101100 !
b11101100 (
b11101100 $
b11101100 '
#238000
b11101101 !
b11101101 (
b11101101 $
b11101101 '
#239000
b11101110 !
b11101110 (
b11101110 $
b11101110 '
#240000
b11101111 !
b11101111 (
b11101111 $
b11101111 '
#241000
b11110000 !
b11110000 (
b11110000 $
b11110000 '
#242000
b11110001 !
b11110001 (
b11110001 $
b11110001 '
#243000
b11110010 !
b11110010 (
b11110010 $
b11110010 '
#244000
b11110011 !
b11110011 (
b11110011 $
b11110011 '
#245000
b11110100 !
b11110100 (
b11110100 $
b11110100 '
#246000
b11110101 !
b11110101 (
b11110101 $
b11110101 '
#247000
b11110110 !
b11110110 (
b11110110 $
b11110110 '
#248000
b11110111 !
b11110111 (
b11110111 $
b11110111 '
#249000
b11111000 !
b11111000 (
b11111000 $
b11111000 '
#250000
b11111001 !
b11111001 (
b11111001 $
b11111001 '
#251000
b11111010 !
b11111010 (
b11111010 $
b11111010 '
#252000
b11111011 !
b11111011 (
b11111011 $
b11111011 '
#253000
b11111100 !
b11111100 (
b11111100 $
b11111100 '
#254000
b11111101 !
b11111101 (
b11111101 $
b11111101 '
#255000
b11111110 !
b11111110 (
b11111110 $
b11111110 '
#256000
b11111111 !
b11111111 (
b11111111 $
b11111111 '
#257000
b1 !
b1 (
b0 $
b0 '
b1 #
b1 &
#258000
b10 !
b10 (
b1 $
b1 '
#259000
b11 !
b11 (
b10 $
b10 '
#260000
b100 !
b100 (
b11 $
b11 '
#261000
b101 !
b101 (
b100 $
b100 '
#262000
b110 !
b110 (
b101 $
b101 '
#263000
b111 !
b111 (
b110 $
b110 '
#264000
b1000 !
b1000 (
b111 $
b111 '
#265000
b1001 !
b1001 (
b1000 $
b1000 '
#266000
b1010 !
b1010 (
b1001 $
b1001 '
#267000
b1011 !
b1011 (
b1010 $
b1010 '
#268000
b1100 !
b1100 (
b1011 $
b1011 '
#269000
b1101 !
b1101 (
b1100 $
b1100 '
#270000
b1110 !
b1110 (
b1101 $
b1101 '
#271000
b1111 !
b1111 (
b1110 $
b1110 '
#272000
b10000 !
b10000 (
b1111 $
b1111 '
#273000
b10001 !
b10001 (
b10000 $
b10000 '
#274000
b10010 !
b10010 (
b10001 $
b10001 '
#275000
b10011 !
b10011 (
b10010 $
b10010 '
#276000
b10100 !
b10100 (
b10011 $
b10011 '
#277000
b10101 !
b10101 (
b10100 $
b10100 '
#278000
b10110 !
b10110 (
b10101 $
b10101 '
#279000
b10111 !
b10111 (
b10110 $
b10110 '
#280000
b11000 !
b11000 (
b10111 $
b10111 '
#281000
b11001 !
b11001 (
b11000 $
b11000 '
#282000
b11010 !
b11010 (
b11001 $
b11001 '
#283000
b11011 !
b11011 (
b11010 $
b11010 '
#284000
b11100 !
b11100 (
b11011 $
b11011 '
#285000
b11101 !
b11101 (
b11100 $
b11100 '
#286000
b11110 !
b11110 (
b11101 $
b11101 '
#287000
b11111 !
b11111 (
b11110 $
b11110 '
#288000
b100000 !
b100000 (
b11111 $
b11111 '
#289000
b100001 !
b100001 (
b100000 $
b100000 '
#290000
b100010 !
b100010 (
b100001 $
b100001 '
#291000
b100011 !
b100011 (
b100010 $
b100010 '
#292000
b100100 !
b100100 (
b100011 $
b100011 '
#293000
b100101 !
b100101 (
b100100 $
b100100 '
#294000
b100110 !
b100110 (
b100101 $
b100101 '
#295000
b100111 !
b100111 (
b100110 $
b100110 '
#296000
b101000 !
b101000 (
b100111 $
b100111 '
#297000
b101001 !
b101001 (
b101000 $
b101000 '
#298000
b101010 !
b101010 (
b101001 $
b101001 '
#299000
b101011 !
b101011 (
b101010 $
b101010 '
#300000
b101100 !
b101100 (
b101011 $
b101011 '
#301000
b101101 !
b101101 (
b101100 $
b101100 '
#302000
b101110 !
b101110 (
b101101 $
b101101 '
#303000
b101111 !
b101111 (
b101110 $
b101110 '
#304000
b110000 !
b110000 (
b101111 $
b101111 '
#305000
b110001 !
b110001 (
b110000 $
b110000 '
#306000
b110010 !
b110010 (
b110001 $
b110001 '
#307000
b110011 !
b110011 (
b110010 $
b110010 '
#308000
b110100 !
b110100 (
b110011 $
b110011 '
#309000
b110101 !
b110101 (
b110100 $
b110100 '
#310000
b110110 !
b110110 (
b110101 $
b110101 '
#311000
b110111 !
b110111 (
b110110 $
b110110 '
#312000
b111000 !
b111000 (
b110111 $
b110111 '
#313000
b111001 !
b111001 (
b111000 $
b111000 '
#314000
b111010 !
b111010 (
b111001 $
b111001 '
#315000
b111011 !
b111011 (
b111010 $
b111010 '
#316000
b111100 !
b111100 (
b111011 $
b111011 '
#317000
b111101 !
b111101 (
b111100 $
b111100 '
#318000
b111110 !
b111110 (
b111101 $
b111101 '
#319000
b111111 !
b111111 (
b111110 $
b111110 '
#320000
b1000000 !
b1000000 (
b111111 $
b111111 '
#321000
b1000001 !
b1000001 (
b1000000 $
b1000000 '
#322000
b1000010 !
b1000010 (
b1000001 $
b1000001 '
#323000
b1000011 !
b1000011 (
b1000010 $
b1000010 '
#324000
b1000100 !
b1000100 (
b1000011 $
b1000011 '
#325000
b1000101 !
b1000101 (
b1000100 $
b1000100 '
#326000
b1000110 !
b1000110 (
b1000101 $
b1000101 '
#327000
b1000111 !
b1000111 (
b1000110 $
b1000110 '
#328000
b1001000 !
b1001000 (
b1000111 $
b1000111 '
#329000
b1001001 !
b1001001 (
b1001000 $
b1001000 '
#330000
b1001010 !
b1001010 (
b1001001 $
b1001001 '
#331000
b1001011 !
b1001011 (
b1001010 $
b1001010 '
#332000
b1001100 !
b1001100 (
b1001011 $
b1001011 '
#333000
b1001101 !
b1001101 (
b1001100 $
b1001100 '
#334000
b1001110 !
b1001110 (
b1001101 $
b1001101 '
#335000
b1001111 !
b1001111 (
b1001110 $
b1001110 '
#336000
b1010000 !
b1010000 (
b1001111 $
b1001111 '
#337000
b1010001 !
b1010001 (
b1010000 $
b1010000 '
#338000
b1010010 !
b1010010 (
b1010001 $
b1010001 '
#339000
b1010011 !
b1010011 (
b1010010 $
b1010010 '
#340000
b1010100 !
b1010100 (
b1010011 $
b1010011 '
#341000
b1010101 !
b1010101 (
b1010100 $
b1010100 '
#342000
b1010110 !
b1010110 (
b1010101 $
b1010101 '
#343000
b1010111 !
b1010111 (
b1010110 $
b1010110 '
#344000
b1011000 !
b1011000 (
b1010111 $
b1010111 '
#345000
b1011001 !
b1011001 (
b1011000 $
b1011000 '
#346000
b1011010 !
b1011010 (
b1011001 $
b1011001 '
#347000
b1011011 !
b1011011 (
b1011010 $
b1011010 '
#348000
b1011100 !
b1011100 (
b1011011 $
b1011011 '
#349000
b1011101 !
b1011101 (
b1011100 $
b1011100 '
#350000
b1011110 !
b1011110 (
b1011101 $
b1011101 '
#351000
b1011111 !
b1011111 (
b1011110 $
b1011110 '
#352000
b1100000 !
b1100000 (
b1011111 $
b1011111 '
#353000
b1100001 !
b1100001 (
b1100000 $
b1100000 '
#354000
b1100010 !
b1100010 (
b1100001 $
b1100001 '
#355000
b1100011 !
b1100011 (
b1100010 $
b1100010 '
#356000
b1100100 !
b1100100 (
b1100011 $
b1100011 '
#357000
b1100101 !
b1100101 (
b1100100 $
b1100100 '
#358000
b1100110 !
b1100110 (
b1100101 $
b1100101 '
#359000
b1100111 !
b1100111 (
b1100110 $
b1100110 '
#360000
b1101000 !
b1101000 (
b1100111 $
b1100111 '
#361000
b1101001 !
b1101001 (
b1101000 $
b1101000 '
#362000
b1101010 !
b1101010 (
b1101001 $
b1101001 '
#363000
b1101011 !
b1101011 (
b1101010 $
b1101010 '
#364000
b1101100 !
b1101100 (
b1101011 $
b1101011 '
#365000
b1101101 !
b1101101 (
b1101100 $
b1101100 '
#366000
b1101110 !
b1101110 (
b1101101 $
b1101101 '
#367000
b1101111 !
b1101111 (
b1101110 $
b1101110 '
#368000
b1110000 !
b1110000 (
b1101111 $
b1101111 '
#369000
b1110001 !
b1110001 (
b1110000 $
b1110000 '
#370000
b1110010 !
b1110010 (
b1110001 $
b1110001 '
#371000
b1110011 !
b1110011 (
b1110010 $
b1110010 '
#372000
b1110100 !
b1110100 (
b1110011 $
b1110011 '
#373000
b1110101 !
b1110101 (
b1110100 $
b1110100 '
#374000
b1110110 !
b1110110 (
b1110101 $
b1110101 '
#375000
b1110111 !
b1110111 (
b1110110 $
b1110110 '
#376000
b1111000 !
b1111000 (
b1110111 $
b1110111 '
#377000
b1111001 !
b1111001 (
b1111000 $
b1111000 '
#378000
b1111010 !
b1111010 (
b1111001 $
b1111001 '
#379000
b1111011 !
b1111011 (
b1111010 $
b1111010 '
#380000
b1111100 !
b1111100 (
b1111011 $
b1111011 '
#381000
b1111101 !
b1111101 (
b1111100 $
b1111100 '
#382000
b1111110 !
b1111110 (
b1111101 $
b1111101 '
#383000
b1111111 !
b1111111 (
b1111110 $
b1111110 '
#384000
b10000000 !
b10000000 (
b1111111 $
b1111111 '
#385000
b10000001 !
b10000001 (
b10000000 $
b10000000 '
#386000
b10000010 !
b10000010 (
b10000001 $
b10000001 '
#387000
b10000011 !
b10000011 (
b10000010 $
b10000010 '
#388000
b10000100 !
b10000100 (
b10000011 $
b10000011 '
#389000
b10000101 !
b10000101 (
b10000100 $
b10000100 '
#390000
b10000110 !
b10000110 (
b10000101 $
b10000101 '
#391000
b10000111 !
b10000111 (
b10000110 $
b10000110 '
#392000
b10001000 !
b10001000 (
b10000111 $
b10000111 '
#393000
b10001001 !
b10001001 (
b10001000 $
b10001000 '
#394000
b10001010 !
b10001010 (
b10001001 $
b10001001 '
#395000
b10001011 !
b10001011 (
b10001010 $
b10001010 '
#396000
b10001100 !
b10001100 (
b10001011 $
b10001011 '
#397000
b10001101 !
b10001101 (
b10001100 $
b10001100 '
#398000
b10001110 !
b10001110 (
b10001101 $
b10001101 '
#399000
b10001111 !
b10001111 (
b10001110 $
b10001110 '
#400000
b10010000 !
b10010000 (
b10001111 $
b10001111 '
#401000
b10010001 !
b10010001 (
b10010000 $
b10010000 '
#402000
b10010010 !
b10010010 (
b10010001 $
b10010001 '
#403000
b10010011 !
b10010011 (
b10010010 $
b10010010 '
#404000
b10010100 !
b10010100 (
b10010011 $
b10010011 '
#405000
b10010101 !
b10010101 (
b10010100 $
b10010100 '
#406000
b10010110 !
b10010110 (
b10010101 $
b10010101 '
#407000
b10010111 !
b10010111 (
b10010110 $
b10010110 '
#408000
b10011000 !
b10011000 (
b10010111 $
b10010111 '
#409000
b10011001 !
b10011001 (
b10011000 $
b10011000 '
#410000
b10011010 !
b10011010 (
b10011001 $
b10011001 '
#411000
b10011011 !
b10011011 (
b10011010 $
b10011010 '
#412000
b10011100 !
b10011100 (
b10011011 $
b10011011 '
#413000
b10011101 !
b10011101 (
b10011100 $
b10011100 '
#414000
b10011110 !
b10011110 (
b10011101 $
b10011101 '
#415000
b10011111 !
b10011111 (
b10011110 $
b10011110 '
#416000
b10100000 !
b10100000 (
b10011111 $
b10011111 '
#417000
b10100001 !
b10100001 (
b10100000 $
b10100000 '
#418000
b10100010 !
b10100010 (
b10100001 $
b10100001 '
#419000
b10100011 !
b10100011 (
b10100010 $
b10100010 '
#420000
b10100100 !
b10100100 (
b10100011 $
b10100011 '
#421000
b10100101 !
b10100101 (
b10100100 $
b10100100 '
#422000
b10100110 !
b10100110 (
b10100101 $
b10100101 '
#423000
b10100111 !
b10100111 (
b10100110 $
b10100110 '
#424000
b10101000 !
b10101000 (
b10100111 $
b10100111 '
#425000
b10101001 !
b10101001 (
b10101000 $
b10101000 '
#426000
b10101010 !
b10101010 (
b10101001 $
b10101001 '
#427000
b10101011 !
b10101011 (
b10101010 $
b10101010 '
#428000
b10101100 !
b10101100 (
b10101011 $
b10101011 '
#429000
b10101101 !
b10101101 (
b10101100 $
b10101100 '
#430000
b10101110 !
b10101110 (
b10101101 $
b10101101 '
#431000
b10101111 !
b10101111 (
b10101110 $
b10101110 '
#432000
b10110000 !
b10110000 (
b10101111 $
b10101111 '
#433000
b10110001 !
b10110001 (
b10110000 $
b10110000 '
#434000
b10110010 !
b10110010 (
b10110001 $
b10110001 '
#435000
b10110011 !
b10110011 (
b10110010 $
b10110010 '
#436000
b10110100 !
b10110100 (
b10110011 $
b10110011 '
#437000
b10110101 !
b10110101 (
b10110100 $
b10110100 '
#438000
b10110110 !
b10110110 (
b10110101 $
b10110101 '
#439000
b10110111 !
b10110111 (
b10110110 $
b10110110 '
#440000
b10111000 !
b10111000 (
b10110111 $
b10110111 '
#441000
b10111001 !
b10111001 (
b10111000 $
b10111000 '
#442000
b10111010 !
b10111010 (
b10111001 $
b10111001 '
#443000
b10111011 !
b10111011 (
b10111010 $
b10111010 '
#444000
b10111100 !
b10111100 (
b10111011 $
b10111011 '
#445000
b10111101 !
b10111101 (
b10111100 $
b10111100 '
#446000
b10111110 !
b10111110 (
b10111101 $
b10111101 '
#447000
b10111111 !
b10111111 (
b10111110 $
b10111110 '
#448000
b11000000 !
b11000000 (
b10111111 $
b10111111 '
#449000
b11000001 !
b11000001 (
b11000000 $
b11000000 '
#450000
b11000010 !
b11000010 (
b11000001 $
b11000001 '
#451000
b11000011 !
b11000011 (
b11000010 $
b11000010 '
#452000
b11000100 !
b11000100 (
b11000011 $
b11000011 '
#453000
b11000101 !
b11000101 (
b11000100 $
b11000100 '
#454000
b11000110 !
b11000110 (
b11000101 $
b11000101 '
#455000
b11000111 !
b11000111 (
b11000110 $
b11000110 '
#456000
b11001000 !
b11001000 (
b11000111 $
b11000111 '
#457000
b11001001 !
b11001001 (
b11001000 $
b11001000 '
#458000
b11001010 !
b11001010 (
b11001001 $
b11001001 '
#459000
b11001011 !
b11001011 (
b11001010 $
b11001010 '
#460000
b11001100 !
b11001100 (
b11001011 $
b11001011 '
#461000
b11001101 !
b11001101 (
b11001100 $
b11001100 '
