Lab5/part 2_3/cont_8bit_adder.v
`timescale 1ns/1ps
module cont_8bit_adder(sum,cout,a,b,cin);
    input [7:0] a,b;
    input cin;
    output [7:0] sum;
    output cout;

    assign {cout,sum} = a+b+cin;
endmodule

Lab5/part_1/testbench_cont_8bit_adder.v
`timescale 1ns/1ps

module testbench_cont_8bit_adder;

reg [7:0] a, b;
reg cin;
wire [7:0] sum;
wire cout;

cont_8bit_adder DUT(sum,cout,a,b,cin);

initial begin
    $dumpfile("cont_8bit_adder.vcd");
    $dumpvars;
end

initial
begin
    a=8'b11110000;
    b=8'b11111111;
    cin = 1'b1;
end

always #1
begin
    a = ( a<<1 | cin);
    $monitor("%4dns monitor: a=%d b=%d cin=%d sum=%d cout=%d",$stime, a, b, cin, sum, cout);
end

always #2 b=b>>2;
always #3 cin = ~cin;
initial #15 $finish;

endmodule

Lab5/part_1/cont_8bit_adder.vcd
$date
	Sun Apr 15 21:08:41 2018
$end
$version
	Icarus Verilog
$end
$timescale
	1ps
$end
$scope module testbench_cont_8bit_adder $end
$var wire 8 ! sum [7:0] $end
$var wire 1 " cout $end
$var reg 8 # a [7:0] $end
$var reg 8 $ b [7:0] $end
$var reg 1 % cin $end
$scope module DUT $end
$var wire 8 & a [7:0] $end
$var wire 8 ' b [7:0] $end
$var wire 1 % cin $end
$var wire 8 ( sum [7:0] $end
$var wire 1 " cout $end
$upscope $end
$upscope $end
$enddefinitions $end
#0
$dumpvars
b11110000 (
b11111111 '
b11110000 &
1%
b11111111 $
b11110000 #
1"
b11110000 !
$end
#1000
b11100001 !
b11100001 (
b11100001 #
b11100001 &
#2000
b11 !
b11 (
b11000011 #
b11000011 &
b111111 $
b111111 '
#3000
0"
b11000101 !
b11000101 (
b10000110 #
b10000110 &
0%
#4000
b11011 !
b11011 (
b1100 #
b1100 &
b1111 $
b1111 '
#5000
b100111 !
b100111 (
b11000 #
b11000 &
#6000
b110101 !
b110101 (
b110001 #
b110001 &
b11 $
b11 '
1%
#7000
b1100111 !
b1100111 (
b1100011 #
b1100011 &
#8000
b11001000 !
b11001000 (
b11000111 #
b11000111 &
b0 $
b0 '
#9000
b10001110 !
b10001110 (
b10001110 #
b10001110 &
0%
#10000
b11100 !
b11100 (
b11100 #
b11100 &
#11000
b111000 !
b111000 (
b111000 #
b111000 &
#12000
b1110010 !
b1110010 (
b1110001 #
b1110001 &
1%
#13000
b11100100 !
b11100100 (
b11100011 #
b11100011 &
#14000
b11001000 !
b11001000 (
b11000111 #
b11000111 &
#15000
b10001110 !
b10001110 (
b10001110 #
b10001110 &
0%
